cevlib/__init__.py
cevlib/calendar.py
cevlib/competitions.py
cevlib/exceptions.py
cevlib/featured.py
cevlib/match.py
cevlib/converters/__init__.py
cevlib/converters/scoreHeroToJson.py
cevlib/helpers/__init__.py
cevlib/helpers/asyncThread.py
cevlib/helpers/dictTool.py
cevlib/types/__init__.py
cevlib/types/competition.py
cevlib/types/iMatch.py
cevlib/types/iType.py
cevlib/types/info.py
cevlib/types/matchPoll.py
cevlib/types/playByPlay.py
cevlib/types/report.py
cevlib/types/results.py
cevlib/types/stats.py
cevlib/types/team.py
cevlib/types/types.py
cevlib-2.0.4.dist-info/METADATA
cevlib-2.0.4.dist-info/WHEEL
cevlib-2.0.4.dist-info/licenses/LICENSE
cevlib-2.0.4.dist-info/RECORD
