Metadata-Version: 2.1
Name: cevlib
Version: 2.0.4
Summary: inofficial python library for cev.eu
Project-URL: Homepage, https://github.com/dxstiny/cevlib
Project-URL: Bug Tracker, https://github.com/dxstiny/cevlib/issues
Author-email: dxstiny <dxstiny.gh@gmail.com>
License: Mozilla Public License Version 2.0
License-File: LICENSE
Classifier: License :: OSI Approved :: MIT License
Classifier: Operating System :: OS Independent
Classifier: Programming Language :: Python :: 3
Requires-Python: >=3.9
